{
  "routes": [
    {
      "method": "GET",
      "path": "/dishes",
      "handler": "dish.find",
      "config": {
        "policies": []
      }
    },
    {
      "method": "GET",
      "path": "/dishes/count",
      "handler": "dish.count",
      "config": {
        "policies": []
      }
    },
    {
      "method": "GET",
      "path": "/dishes/:id",
      "handler": "dish.findOne",
      "config": {
        "policies": []
      }
    },
    {
      "method": "POST",
      "path": "/dishes",
      "handler": "dish.create",
      "config": {
        "policies": []
      }
    },
    {
      "method": "PUT",
      "path": "/dishes/:id",
      "handler": "dish.update",
      "config": {
        "policies": []
      }
    },
    {
      "method": "DELETE",
      "path": "/dishes/:id",
      "handler": "dish.delete",
      "config": {
        "policies": []
      }
    }
  ]
}
